searchengine/__init__.py
searchengine_v1-0.2.dist-info/LICENSE
searchengine_v1-0.2.dist-info/METADATA
searchengine_v1-0.2.dist-info/WHEEL
searchengine_v1-0.2.dist-info/top_level.txt
searchengine_v1-0.2.dist-info/RECORD
