Metadata-Version: 2.1
Name: searchengine_v1
Version: 0.2
Summary: A lightweight semantic search engine using transformer embeddings.
Home-page: https://github.com/Falgit1/searchengine
Author: Parth Honkalse
Classifier: Programming Language :: Python :: 3
Classifier: License :: OSI Approved :: MIT License
Requires-Python: >=3.7
License-File: LICENSE
Requires-Dist: torch >=1.7.0
Requires-Dist: transformers >=4.0.0
Requires-Dist: scikit-learn >=0.24.0
